plot_gsheets/__init__.py
plot_gsheets/credentials.json
plot_gsheets/token.pickle
plot_gsheets-0.4.dist-info/METADATA
plot_gsheets-0.4.dist-info/WHEEL
plot_gsheets-0.4.dist-info/top_level.txt
plot_gsheets-0.4.dist-info/RECORD
